bondzai.idetect40_interface-0.1.9-py3.10-nspkg.pth
bondzai/idetect40_interface/__init__.py
bondzai/idetect40_interface/exchange_table.py
bondzai/idetect40_interface/socket.py
build/lib/bondzai/idetect40_interface/__init__.py
build/lib/bondzai/idetect40_interface/exchange_table.py
build/lib/bondzai/idetect40_interface/socket.py
build/lib/tests/__init__.py
build/lib/tests/test_exchange_table.py
build/lib/tests/test_socket.py
tests/__init__.py
tests/test_exchange_table.py
tests/test_socket.py
bondzai.idetect40_interface-0.1.9.dist-info/METADATA
bondzai.idetect40_interface-0.1.9.dist-info/NOTICE
bondzai.idetect40_interface-0.1.9.dist-info/WHEEL
bondzai.idetect40_interface-0.1.9.dist-info/namespace_packages.txt
bondzai.idetect40_interface-0.1.9.dist-info/top_level.txt
bondzai.idetect40_interface-0.1.9.dist-info/zip-safe
bondzai.idetect40_interface-0.1.9.dist-info/RECORD
