Metadata-Version: 2.1
Name: bondzai.idetect40-interface
Version: 0.1.9
Summary: Bondzai iDetect 4.0 interface
Home-page: UNKNOWN
Author: Bondzai
License: Apache License 2.0
Keywords: davinsy,bondzai,idetect40
Platform: UNKNOWN
Classifier: Programming Language :: Python :: 3
Classifier: License :: OSI Approved :: Apache Software License
Classifier: Operating System :: OS Independent
License-File: NOTICE
Requires-Dist: numpy (==2.0.2)
Provides-Extra: dev
Requires-Dist: pytest (==7.2.0) ; extra == 'dev'
